azy/__init__.py
azy-0.0.1.dist-info/METADATA
azy-0.0.1.dist-info/WHEEL
azy-0.0.1.dist-info/entry_points.txt
azy-0.0.1.dist-info/top_level.txt
azy-0.0.1.dist-info/RECORD
