Metadata-Version: 2.1
Name: azy
Version: 0.0.1
Summary: A Python package for intelligent information bagging system
Home-page: https://github.com/lqxnjk/azy
Author: lqxnjk
Author-email: lqxnjk@qq.com
License: MIT
Project-URL: Bug Reports, https://github.com/lqxnjk/azy/issues
Project-URL: Source, https://github.com/lqxnjk/azy
Keywords: ii,etls,lqxnjk,data
Platform: UNKNOWN
Classifier: Development Status :: 3 - Alpha
Classifier: Intended Audience :: Developers
Classifier: Intended Audience :: Science/Research
Classifier: Programming Language :: Python :: 3.7
Classifier: License :: OSI Approved :: MIT License
Classifier: Operating System :: OS Independent
Classifier: Topic :: Software Development :: Libraries
Classifier: Topic :: Scientific/Engineering
Requires-Python: >=3.7
Requires-Dist: typing-extensions ; python_version < "3.8"
Provides-Extra: all
Requires-Dist: azy[dev] ; extra == 'all'
Requires-Dist: azy[plot] ; extra == 'all'
Provides-Extra: dev
Provides-Extra: gpu
Provides-Extra: plot
